setup.py
candel_pos_ex_forex_next3/__init__.py
candel_pos_ex_forex_next3/candel_pos_ex_forex_next3.py
candel_pos_ex_forex_next3.egg-info/PKG-INFO
candel_pos_ex_forex_next3.egg-info/SOURCES.txt
candel_pos_ex_forex_next3.egg-info/dependency_links.txt
candel_pos_ex_forex_next3.egg-info/not-zip-safe
candel_pos_ex_forex_next3.egg-info/top_level.txt